spintax/__init__.py
spintax/spintax.py
spintax-1.0.4.dist-info/LICENCE
spintax-1.0.4.dist-info/METADATA
spintax-1.0.4.dist-info/WHEEL
spintax-1.0.4.dist-info/top_level.txt
spintax-1.0.4.dist-info/RECORD
